cimg_desc/__init__.py
cimg_desc/handler.py
cimg_desc/model.py
cimg_desc/predictor.py
cimg_desc/retro_rcts_199.pt
cimg_desc-0.0.1.dist-info/METADATA
cimg_desc-0.0.1.dist-info/WHEEL
cimg_desc-0.0.1.dist-info/top_level.txt
cimg_desc-0.0.1.dist-info/RECORD
